gym_flp/__init__.py
gym_flp/algorithm/__init__.py
gym_flp/algorithm/eval.py
gym_flp/algorithm/train.py
gym_flp/envs/FBS.py
gym_flp/envs/OFP.py
gym_flp/envs/QAP.py
gym_flp/envs/STS.py
gym_flp/envs/__init__.py
gym_flp/envs/instances/__init__.py
gym_flp/envs/instances/_assemble_instance_json.py
gym_flp/envs/instances/envBuilder.py
gym_flp/rewards/__init__.py
gym_flp/rewards/area.py
gym_flp/rewards/distances.py
gym_flp/rewards/mhc.py
gym_flp/util/__init__.py
gym_flp/util/preprocessing.py
testing/__init__.py
testing/version_test.py
testing/unit/__init__.py
testing/unit/normalization.py
testing/unit/test_collision.py
testing/unit/test_rescaling.py
gym_flp-0.2.11.dist-info/LICENSE
gym_flp-0.2.11.dist-info/METADATA
gym_flp-0.2.11.dist-info/WHEEL
gym_flp-0.2.11.dist-info/top_level.txt
gym_flp-0.2.11.dist-info/RECORD
